{"total":13,"p":1,"ps":100,"paging":{"pageIndex":1,"pageSize":100,"total":13},"effortTotal":149,"issues":[{"key":"AYAn6pLc9L-ZhL7_PiAx","rule":"java:S107","severity":"MAJOR","component":"at.lucny.p2pbackup:p2pbackup:application/src/main/java/at/lucny/p2pbackup/restore/service/RestorationServiceImpl.java","project":"at.lucny.p2pbackup:p2pbackup","line":72,"hash":"e4667c9d461b61eb9021adc000cca3bf","textRange":{"startLine":72,"endLine":72,"startOffset":11,"endOffset":33},"flows":[],"resolution":"WONTFIX","status":"RESOLVED","message":"Constructor has 9 parameters, which is greater than 7 authorized.","effort":"20min","debt":"20min","author":"gl.github.com@lucny.at","tags":["brain-overload"],"comments":[{"key":"AYAoG8oEEKbwgZF1i3Vj","login":"admin","htmlText":"The restoration service needs all the dependencies.","markdown":"The restoration service needs all the dependencies.","updatable":true,"createdAt":"2022-04-14T12:45:51+0000"}],"creationDate":"2022-04-14T11:51:06+0000","updateDate":"2022-04-14T12:45:51+0000","type":"CODE_SMELL","scope":"MAIN","quickFixAvailable":false},{"key":"AYAYmfrCFgRb6d8dcCvC","rule":"java:S3776","severity":"CRITICAL","component":"at.lucny.p2pbackup:p2pbackup:application/src/main/java/at/lucny/p2pbackup/upload/service/DistributionServiceImpl.java","project":"at.lucny.p2pbackup:p2pbackup","line":91,"hash":"ee050c1adb41b6e194e5dc5b60b1fa65","textRange":{"startLine":91,"endLine":91,"startOffset":16,"endOffset":32},"flows":[{"locations":[{"component":"at.lucny.p2pbackup:p2pbackup:application/src/main/java/at/lucny/p2pbackup/upload/service/DistributionServiceImpl.java","textRange":{"startLine":95,"endLine":95,"startOffset":8,"endOffset":10},"msg":"+1"}]},{"locations":[{"component":"at.lucny.p2pbackup:p2pbackup:application/src/main/java/at/lucny/p2pbackup/upload/service/DistributionServiceImpl.java","textRange":{"startLine":101,"endLine":101,"startOffset":8,"endOffset":10},"msg":"+1"}]},{"locations":[{"component":"at.lucny.p2pbackup:p2pbackup:application/src/main/java/at/lucny/p2pbackup/upload/service/DistributionServiceImpl.java","textRange":{"startLine":113,"endLine":113,"startOffset":8,"endOffset":11},"msg":"+1"}]},{"locations":[{"component":"at.lucny.p2pbackup:p2pbackup:application/src/main/java/at/lucny/p2pbackup/upload/service/DistributionServiceImpl.java","textRange":{"startLine":116,"endLine":116,"startOffset":12,"endOffset":15},"msg":"+2 (incl 1 for nesting)"}]},{"locations":[{"component":"at.lucny.p2pbackup:p2pbackup:application/src/main/java/at/lucny/p2pbackup/upload/service/DistributionServiceImpl.java","textRange":{"startLine":120,"endLine":120,"startOffset":16,"endOffset":18},"msg":"+3 (incl 2 for nesting)"}]},{"locations":[{"component":"at.lucny.p2pbackup:p2pbackup:application/src/main/java/at/lucny/p2pbackup/upload/service/DistributionServiceImpl.java","textRange":{"startLine":126,"endLine":126,"startOffset":16,"endOffset":18},"msg":"+3 (incl 2 for nesting)"}]},{"locations":[{"component":"at.lucny.p2pbackup:p2pbackup:application/src/main/java/at/lucny/p2pbackup/upload/service/DistributionServiceImpl.java","textRange":{"startLine":131,"endLine":131,"startOffset":16,"endOffset":18},"msg":"+3 (incl 2 for nesting)"}]},{"locations":[{"component":"at.lucny.p2pbackup:p2pbackup:application/src/main/java/at/lucny/p2pbackup/upload/service/DistributionServiceImpl.java","textRange":{"startLine":137,"endLine":137,"startOffset":8,"endOffset":10},"msg":"+1"}]},{"locations":[{"component":"at.lucny.p2pbackup:p2pbackup:application/src/main/java/at/lucny/p2pbackup/upload/service/DistributionServiceImpl.java","textRange":{"startLine":141,"endLine":141,"startOffset":8,"endOffset":10},"msg":"+1"}]}],"resolution":"WONTFIX","status":"RESOLVED","message":"Refactor this method to reduce its Cognitive Complexity from 16 to the 15 allowed.","effort":"6min","debt":"6min","author":"gl.github.com@lucny.at","tags":["brain-overload"],"comments":[{"key":"AYAoF5p7EKbwgZF1i3U2","login":"admin","htmlText":"Complexity is higher because of log-statements","markdown":"Complexity is higher because of log-statements","updatable":true,"createdAt":"2022-04-14T12:41:17+0000"}],"creationDate":"2022-04-11T12:28:23+0000","updateDate":"2022-04-14T12:50:00+0000","type":"CODE_SMELL","scope":"MAIN","quickFixAvailable":false},{"key":"AYAYmfoWFgRb6d8dcCu-","rule":"java:S1192","severity":"CRITICAL","component":"at.lucny.p2pbackup:p2pbackup:application/src/main/java/at/lucny/p2pbackup/user/service/UserServiceImpl.java","project":"at.lucny.p2pbackup:p2pbackup","line":74,"hash":"10804fe5c01c027e4d60ce0b6aae8290","textRange":{"startLine":74,"endLine":74,"startOffset":24,"endOffset":48},"flows":[{"locations":[{"component":"at.lucny.p2pbackup:p2pbackup:application/src/main/java/at/lucny/p2pbackup/user/service/UserServiceImpl.java","textRange":{"startLine":74,"endLine":74,"startOffset":24,"endOffset":48},"msg":"Duplication"}]},{"locations":[{"component":"at.lucny.p2pbackup:p2pbackup:application/src/main/java/at/lucny/p2pbackup/user/service/UserServiceImpl.java","textRange":{"startLine":96,"endLine":96,"startOffset":24,"endOffset":48},"msg":"Duplication"}]},{"locations":[{"component":"at.lucny.p2pbackup:p2pbackup:application/src/main/java/at/lucny/p2pbackup/user/service/UserServiceImpl.java","textRange":{"startLine":135,"endLine":135,"startOffset":24,"endOffset":48},"msg":"Duplication"}]}],"resolution":"WONTFIX","status":"RESOLVED","message":"Define a constant instead of duplicating this literal \"User {} does not exist\" 3 times.","effort":"8min","debt":"8min","author":"gl.github.com@lucny.at","tags":["design"],"comments":[{"key":"AYAn-4mGEKbwgZF1i3TV","login":"admin","htmlText":"Rule does not apply on log-statements","markdown":"Rule does not apply on log-statements","updatable":true,"createdAt":"2022-04-14T12:10:37+0000"}],"creationDate":"2022-04-11T12:28:23+0000","updateDate":"2022-04-14T12:10:37+0000","type":"CODE_SMELL","scope":"MAIN","quickFixAvailable":false},{"key":"AX_7Eby9gXukmhArAAti","rule":"java:S2629","severity":"MAJOR","component":"at.lucny.p2pbackup:p2pbackup:application/src/main/java/at/lucny/p2pbackup/protocol/service/handler/UtilsHandler.java","project":"at.lucny.p2pbackup:p2pbackup","line":25,"hash":"f87cea79a2bbe29b6332d39457fdab9b","textRange":{"startLine":25,"endLine":25,"startOffset":39,"endOffset":70},"flows":[],"resolution":"WONTFIX","status":"RESOLVED","message":"Invoke method(s) only conditionally.","effort":"5min","debt":"5min","author":"gl.github.com@lucny.at","tags":["performance"],"comments":[{"key":"AX_7JuKGUTh-wf1O5Q0o","login":"admin","htmlText":"call of a record-method","markdown":"call of a record-method","updatable":true,"createdAt":"2022-04-05T19:15:03+0000"}],"creationDate":"2022-04-05T18:51:10+0000","updateDate":"2022-04-05T19:15:03+0000","type":"CODE_SMELL","scope":"MAIN","quickFixAvailable":false},{"key":"AX_5rFnDgXukmhAr_xXA","rule":"java:S1192","severity":"CRITICAL","component":"at.lucny.p2pbackup:p2pbackup:cloud.googledrive/src/main/java/at/lucny/p2pbackup/cloud/googledrive/service/GoogleDriveStorageServiceImpl.java","project":"at.lucny.p2pbackup:p2pbackup","line":173,"hash":"1458e12996e07f77c41c3bbf59c8bd8e","textRange":{"startLine":173,"endLine":173,"startOffset":47,"endOffset":54},"flows":[{"locations":[{"component":"at.lucny.p2pbackup:p2pbackup:cloud.googledrive/src/main/java/at/lucny/p2pbackup/cloud/googledrive/service/GoogleDriveStorageServiceImpl.java","textRange":{"startLine":173,"endLine":173,"startOffset":47,"endOffset":54},"msg":"Duplication"}]},{"locations":[{"component":"at.lucny.p2pbackup:p2pbackup:cloud.googledrive/src/main/java/at/lucny/p2pbackup/cloud/googledrive/service/GoogleDriveStorageServiceImpl.java","textRange":{"startLine":176,"endLine":176,"startOffset":47,"endOffset":54},"msg":"Duplication"}]},{"locations":[{"component":"at.lucny.p2pbackup:p2pbackup:cloud.googledrive/src/main/java/at/lucny/p2pbackup/cloud/googledrive/service/GoogleDriveStorageServiceImpl.java","textRange":{"startLine":179,"endLine":179,"startOffset":47,"endOffset":54},"msg":"Duplication"}]}],"resolution":"WONTFIX","status":"RESOLVED","message":"Define a constant instead of duplicating this literal \"path \" 3 times.","effort":"8min","debt":"8min","author":"gl.github.com@lucny.at","tags":["design"],"comments":[{"key":"AYAIHyKjK8HgEqrRvbSB","login":"admin","htmlText":"rule does not apply for exception-strings","markdown":"rule does not apply for exception-strings","updatable":true,"createdAt":"2022-04-08T07:41:39+0000"}],"creationDate":"2022-04-05T12:20:08+0000","updateDate":"2022-04-08T07:41:39+0000","type":"CODE_SMELL","scope":"MAIN","quickFixAvailable":false},{"key":"AX_5rFldgXukmhAr_xW7","rule":"common-java:DuplicatedBlocks","severity":"MAJOR","component":"at.lucny.p2pbackup:p2pbackup:cloud.nextcloud/src/main/java/at/lucny/p2pbackup/cloud/nextcloud/service/NextcloudStorageServiceImpl.java","project":"at.lucny.p2pbackup:p2pbackup","flows":[],"resolution":"WONTFIX","status":"RESOLVED","message":"1 duplicated blocks of code must be removed.","effort":"20min","debt":"20min","author":"gl.github.com@lucny.at","tags":["pitfall"],"comments":[{"key":"AYAII1HoK8HgEqrRvbVG","login":"admin","htmlText":"rule is deprecated","markdown":"rule is deprecated","updatable":true,"createdAt":"2022-04-08T07:46:14+0000"}],"creationDate":"2022-04-05T12:20:08+0000","updateDate":"2022-04-08T07:46:14+0000","type":"CODE_SMELL","scope":"MAIN","quickFixAvailable":false},{"key":"AX_5rFlegXukmhAr_xW8","rule":"java:S1192","severity":"CRITICAL","component":"at.lucny.p2pbackup:p2pbackup:cloud.nextcloud/src/main/java/at/lucny/p2pbackup/cloud/nextcloud/service/NextcloudStorageServiceImpl.java","project":"at.lucny.p2pbackup:p2pbackup","line":82,"hash":"f5042ef60b8ec37d0bbe547956eaafcb","textRange":{"startLine":82,"endLine":82,"startOffset":105,"endOffset":142},"flows":[{"locations":[{"component":"at.lucny.p2pbackup:p2pbackup:cloud.nextcloud/src/main/java/at/lucny/p2pbackup/cloud/nextcloud/service/NextcloudStorageServiceImpl.java","textRange":{"startLine":82,"endLine":82,"startOffset":105,"endOffset":142},"msg":"Duplication"}]},{"locations":[{"component":"at.lucny.p2pbackup:p2pbackup:cloud.nextcloud/src/main/java/at/lucny/p2pbackup/cloud/nextcloud/service/NextcloudStorageServiceImpl.java","textRange":{"startLine":83,"endLine":83,"startOffset":100,"endOffset":137},"msg":"Duplication"}]},{"locations":[{"component":"at.lucny.p2pbackup:p2pbackup:cloud.nextcloud/src/main/java/at/lucny/p2pbackup/cloud/nextcloud/service/NextcloudStorageServiceImpl.java","textRange":{"startLine":84,"endLine":84,"startOffset":100,"endOffset":137},"msg":"Duplication"}]}],"resolution":"WONTFIX","status":"RESOLVED","message":"Define a constant instead of duplicating this literal \"nextcloud not configured, property \" 3 times.","effort":"8min","debt":"8min","author":"gl.github.com@lucny.at","tags":["design"],"comments":[{"key":"AYAIH5TwK8HgEqrRvbSy","login":"admin","htmlText":"rule does not apply for exception-strings","markdown":"rule does not apply for exception-strings","updatable":true,"createdAt":"2022-04-08T07:42:09+0000"}],"creationDate":"2022-04-05T12:20:08+0000","updateDate":"2022-04-08T07:42:09+0000","type":"CODE_SMELL","scope":"MAIN","quickFixAvailable":false},{"key":"AX_5rFlegXukmhAr_xW9","rule":"java:S1192","severity":"CRITICAL","component":"at.lucny.p2pbackup:p2pbackup:cloud.nextcloud/src/main/java/at/lucny/p2pbackup/cloud/nextcloud/service/NextcloudStorageServiceImpl.java","project":"at.lucny.p2pbackup:p2pbackup","line":82,"hash":"f5042ef60b8ec37d0bbe547956eaafcb","textRange":{"startLine":82,"endLine":82,"startOffset":170,"endOffset":180},"flows":[{"locations":[{"component":"at.lucny.p2pbackup:p2pbackup:cloud.nextcloud/src/main/java/at/lucny/p2pbackup/cloud/nextcloud/service/NextcloudStorageServiceImpl.java","textRange":{"startLine":82,"endLine":82,"startOffset":170,"endOffset":180},"msg":"Duplication"}]},{"locations":[{"component":"at.lucny.p2pbackup:p2pbackup:cloud.nextcloud/src/main/java/at/lucny/p2pbackup/cloud/nextcloud/service/NextcloudStorageServiceImpl.java","textRange":{"startLine":83,"endLine":83,"startOffset":162,"endOffset":172},"msg":"Duplication"}]},{"locations":[{"component":"at.lucny.p2pbackup:p2pbackup:cloud.nextcloud/src/main/java/at/lucny/p2pbackup/cloud/nextcloud/service/NextcloudStorageServiceImpl.java","textRange":{"startLine":84,"endLine":84,"startOffset":162,"endOffset":172},"msg":"Duplication"}]}],"resolution":"WONTFIX","status":"RESOLVED","message":"Define a constant instead of duplicating this literal \" missing\" 3 times.","effort":"8min","debt":"8min","author":"gl.github.com@lucny.at","tags":["design"],"comments":[{"key":"AYAIH-XKK8HgEqrRvbS6","login":"admin","htmlText":"rule does not apply for exception-strings","markdown":"rule does not apply for exception-strings","updatable":true,"createdAt":"2022-04-08T07:42:29+0000"}],"creationDate":"2022-04-05T12:20:08+0000","updateDate":"2022-04-08T07:42:29+0000","type":"CODE_SMELL","scope":"MAIN","quickFixAvailable":false},{"key":"AX_5rFemgXukmhAr_xWH","rule":"java:S1192","severity":"CRITICAL","component":"at.lucny.p2pbackup:p2pbackup:application/src/main/java/at/lucny/p2pbackup/verification/service/VerificationServiceImpl.java","project":"at.lucny.p2pbackup:p2pbackup","line":223,"hash":"7e85f6da76dd4e2ffb5b3c168146b851","textRange":{"startLine":223,"endLine":223,"startOffset":25,"endOffset":80},"flows":[{"locations":[{"component":"at.lucny.p2pbackup:p2pbackup:application/src/main/java/at/lucny/p2pbackup/verification/service/VerificationServiceImpl.java","textRange":{"startLine":223,"endLine":223,"startOffset":25,"endOffset":80},"msg":"Duplication"}]},{"locations":[{"component":"at.lucny.p2pbackup:p2pbackup:application/src/main/java/at/lucny/p2pbackup/verification/service/VerificationServiceImpl.java","textRange":{"startLine":235,"endLine":235,"startOffset":25,"endOffset":80},"msg":"Duplication"}]},{"locations":[{"component":"at.lucny.p2pbackup:p2pbackup:application/src/main/java/at/lucny/p2pbackup/verification/service/VerificationServiceImpl.java","textRange":{"startLine":281,"endLine":281,"startOffset":25,"endOffset":80},"msg":"Duplication"}]}],"resolution":"WONTFIX","status":"RESOLVED","message":"Define a constant instead of duplicating this literal \"data-location for block {} and user {} does not exist\" 3 times.","effort":"8min","debt":"8min","author":"gl.github.com@lucny.at","tags":["design"],"comments":[{"key":"AYAIIc2QK8HgEqrRvbTm","login":"admin","htmlText":"rule does not apply on log-statements","markdown":"rule does not apply on log-statements","updatable":true,"createdAt":"2022-04-08T07:44:34+0000"}],"creationDate":"2022-03-11T16:51:53+0000","updateDate":"2022-04-08T07:44:34+0000","type":"CODE_SMELL","scope":"MAIN","quickFixAvailable":false},{"key":"AX_5rFYggXukmhAr_xVz","rule":"java:S1192","severity":"CRITICAL","component":"at.lucny.p2pbackup:p2pbackup:application/src/main/java/at/lucny/p2pbackup/localstorage/service/LocalStorageServiceImpl.java","project":"at.lucny.p2pbackup:p2pbackup","line":178,"hash":"8fed4f4542258fbe7ed1a19c6b2e1374","textRange":{"startLine":178,"endLine":178,"startOffset":25,"endOffset":67},"flows":[{"locations":[{"component":"at.lucny.p2pbackup:p2pbackup:application/src/main/java/at/lucny/p2pbackup/localstorage/service/LocalStorageServiceImpl.java","textRange":{"startLine":178,"endLine":178,"startOffset":25,"endOffset":67},"msg":"Duplication"}]},{"locations":[{"component":"at.lucny.p2pbackup:p2pbackup:application/src/main/java/at/lucny/p2pbackup/localstorage/service/LocalStorageServiceImpl.java","textRange":{"startLine":190,"endLine":190,"startOffset":33,"endOffset":75},"msg":"Duplication"}]},{"locations":[{"component":"at.lucny.p2pbackup:p2pbackup:application/src/main/java/at/lucny/p2pbackup/localstorage/service/LocalStorageServiceImpl.java","textRange":{"startLine":194,"endLine":194,"startOffset":33,"endOffset":75},"msg":"Duplication"}]},{"locations":[{"component":"at.lucny.p2pbackup:p2pbackup:application/src/main/java/at/lucny/p2pbackup/localstorage/service/LocalStorageServiceImpl.java","textRange":{"startLine":199,"endLine":199,"startOffset":29,"endOffset":71},"msg":"Duplication"}]},{"locations":[{"component":"at.lucny.p2pbackup:p2pbackup:application/src/main/java/at/lucny/p2pbackup/localstorage/service/LocalStorageServiceImpl.java","textRange":{"startLine":211,"endLine":211,"startOffset":25,"endOffset":67},"msg":"Duplication"}]},{"locations":[{"component":"at.lucny.p2pbackup:p2pbackup:application/src/main/java/at/lucny/p2pbackup/localstorage/service/LocalStorageServiceImpl.java","textRange":{"startLine":216,"endLine":216,"startOffset":25,"endOffset":67},"msg":"Duplication"}]},{"locations":[{"component":"at.lucny.p2pbackup:p2pbackup:application/src/main/java/at/lucny/p2pbackup/localstorage/service/LocalStorageServiceImpl.java","textRange":{"startLine":227,"endLine":227,"startOffset":25,"endOffset":67},"msg":"Duplication"}]}],"resolution":"WONTFIX","status":"RESOLVED","message":"Define a constant instead of duplicating this literal \"end saveFromUserInLocalBackup: return {}\" 7 times.","effort":"16min","debt":"16min","author":"gl.github.com@lucny.at","tags":["design"],"comments":[{"key":"AYAIHkqWK8HgEqrRvbQo","login":"admin","htmlText":"rule does not apply for log-strings","markdown":"rule does not apply for log-strings","updatable":true,"createdAt":"2022-04-08T07:40:44+0000"}],"creationDate":"2022-02-24T20:11:06+0000","updateDate":"2022-04-11T12:28:23+0000","type":"CODE_SMELL","scope":"MAIN","quickFixAvailable":false},{"key":"AX_5rFmcgXukmhAr_xW-","rule":"common-java:DuplicatedBlocks","severity":"MAJOR","component":"at.lucny.p2pbackup:p2pbackup:cloud.filesystem/src/main/java/at/lucny/p2pbackup/cloud/filesystem/service/FilesystemStorageServiceImpl.java","project":"at.lucny.p2pbackup:p2pbackup","flows":[],"resolution":"WONTFIX","status":"RESOLVED","message":"1 duplicated blocks of code must be removed.","effort":"20min","debt":"20min","author":"gl.github.com@lucny.at","tags":["pitfall"],"comments":[{"key":"AYAIIzahK8HgEqrRvbUV","login":"admin","htmlText":"rule is deprecated","markdown":"rule is deprecated","updatable":true,"createdAt":"2022-04-08T07:46:07+0000"}],"creationDate":"2022-01-07T12:59:00+0000","updateDate":"2022-04-08T07:46:07+0000","type":"CODE_SMELL","scope":"MAIN","quickFixAvailable":false},{"key":"AX_5rFmcgXukmhAr_xW_","rule":"java:S1192","severity":"CRITICAL","component":"at.lucny.p2pbackup:p2pbackup:cloud.filesystem/src/main/java/at/lucny/p2pbackup/cloud/filesystem/service/FilesystemStorageServiceImpl.java","project":"at.lucny.p2pbackup:p2pbackup","line":80,"hash":"1458e12996e07f77c41c3bbf59c8bd8e","textRange":{"startLine":80,"endLine":80,"startOffset":47,"endOffset":54},"flows":[{"locations":[{"component":"at.lucny.p2pbackup:p2pbackup:cloud.filesystem/src/main/java/at/lucny/p2pbackup/cloud/filesystem/service/FilesystemStorageServiceImpl.java","textRange":{"startLine":80,"endLine":80,"startOffset":47,"endOffset":54},"msg":"Duplication"}]},{"locations":[{"component":"at.lucny.p2pbackup:p2pbackup:cloud.filesystem/src/main/java/at/lucny/p2pbackup/cloud/filesystem/service/FilesystemStorageServiceImpl.java","textRange":{"startLine":83,"endLine":83,"startOffset":47,"endOffset":54},"msg":"Duplication"}]},{"locations":[{"component":"at.lucny.p2pbackup:p2pbackup:cloud.filesystem/src/main/java/at/lucny/p2pbackup/cloud/filesystem/service/FilesystemStorageServiceImpl.java","textRange":{"startLine":86,"endLine":86,"startOffset":47,"endOffset":54},"msg":"Duplication"}]},{"locations":[{"component":"at.lucny.p2pbackup:p2pbackup:cloud.filesystem/src/main/java/at/lucny/p2pbackup/cloud/filesystem/service/FilesystemStorageServiceImpl.java","textRange":{"startLine":100,"endLine":100,"startOffset":47,"endOffset":54},"msg":"Duplication"}]},{"locations":[{"component":"at.lucny.p2pbackup:p2pbackup:cloud.filesystem/src/main/java/at/lucny/p2pbackup/cloud/filesystem/service/FilesystemStorageServiceImpl.java","textRange":{"startLine":103,"endLine":103,"startOffset":47,"endOffset":54},"msg":"Duplication"}]},{"locations":[{"component":"at.lucny.p2pbackup:p2pbackup:cloud.filesystem/src/main/java/at/lucny/p2pbackup/cloud/filesystem/service/FilesystemStorageServiceImpl.java","textRange":{"startLine":106,"endLine":106,"startOffset":47,"endOffset":54},"msg":"Duplication"}]}],"resolution":"WONTFIX","status":"RESOLVED","message":"Define a constant instead of duplicating this literal \"path \" 6 times.","effort":"14min","debt":"14min","author":"gl.github.com@lucny.at","tags":["design"],"comments":[{"key":"AYAIHuKXK8HgEqrRvbRV","login":"admin","htmlText":"rule does not apply for exception-strings","markdown":"rule does not apply for exception-strings","updatable":true,"createdAt":"2022-04-08T07:41:23+0000"}],"creationDate":"2021-12-31T11:31:58+0000","updateDate":"2022-04-08T07:41:23+0000","type":"CODE_SMELL","scope":"MAIN","quickFixAvailable":false},{"key":"AX2BJazNDg-nxKy3wz6G","rule":"java:S1192","severity":"CRITICAL","component":"at.lucny.p2pbackup:p2pbackup:cloud.nextcloud/src/main/java/at/lucny/p2pbackup/cloud/nextcloud/service/NextcloudStorageServiceImpl.java","project":"at.lucny.p2pbackup:p2pbackup","line":137,"hash":"1458e12996e07f77c41c3bbf59c8bd8e","textRange":{"startLine":137,"endLine":137,"startOffset":47,"endOffset":54},"flows":[{"locations":[{"component":"at.lucny.p2pbackup:p2pbackup:cloud.nextcloud/src/main/java/at/lucny/p2pbackup/cloud/nextcloud/service/NextcloudStorageServiceImpl.java","textRange":{"startLine":137,"endLine":137,"startOffset":47,"endOffset":54},"msg":"Duplication"}]},{"locations":[{"component":"at.lucny.p2pbackup:p2pbackup:cloud.nextcloud/src/main/java/at/lucny/p2pbackup/cloud/nextcloud/service/NextcloudStorageServiceImpl.java","textRange":{"startLine":140,"endLine":140,"startOffset":47,"endOffset":54},"msg":"Duplication"}]},{"locations":[{"component":"at.lucny.p2pbackup:p2pbackup:cloud.nextcloud/src/main/java/at/lucny/p2pbackup/cloud/nextcloud/service/NextcloudStorageServiceImpl.java","textRange":{"startLine":143,"endLine":143,"startOffset":47,"endOffset":54},"msg":"Duplication"}]}],"resolution":"WONTFIX","status":"RESOLVED","message":"Define a constant instead of duplicating this literal \"path \" 3 times.","effort":"8min","debt":"8min","author":"gl.github.com@lucny.at","tags":["design"],"comments":[{"key":"AYAIJtoKK8HgEqrRvbVU","login":"admin","htmlText":"rule does not apply to exception-strings","markdown":"rule does not apply to exception-strings","updatable":true,"createdAt":"2022-04-08T07:50:05+0000"}],"creationDate":"2021-11-28T20:29:12+0000","updateDate":"2022-04-08T07:50:05+0000","type":"CODE_SMELL","scope":"MAIN","quickFixAvailable":false}],"components":[{"key":"at.lucny.p2pbackup:p2pbackup:cloud.googledrive/src/main/java/at/lucny/p2pbackup/cloud/googledrive/service/GoogleDriveStorageServiceImpl.java","enabled":true,"qualifier":"FIL","name":"GoogleDriveStorageServiceImpl.java","longName":"cloud.googledrive/src/main/java/at/lucny/p2pbackup/cloud/googledrive/service/GoogleDriveStorageServiceImpl.java","path":"cloud.googledrive/src/main/java/at/lucny/p2pbackup/cloud/googledrive/service/GoogleDriveStorageServiceImpl.java"},{"key":"at.lucny.p2pbackup:p2pbackup:application/src/main/java/at/lucny/p2pbackup/localstorage/service/LocalStorageServiceImpl.java","enabled":true,"qualifier":"FIL","name":"LocalStorageServiceImpl.java","longName":"application/src/main/java/at/lucny/p2pbackup/localstorage/service/LocalStorageServiceImpl.java","path":"application/src/main/java/at/lucny/p2pbackup/localstorage/service/LocalStorageServiceImpl.java"},{"key":"at.lucny.p2pbackup:p2pbackup:application/src/main/java/at/lucny/p2pbackup/protocol/service/handler/UtilsHandler.java","enabled":true,"qualifier":"FIL","name":"UtilsHandler.java","longName":"application/src/main/java/at/lucny/p2pbackup/protocol/service/handler/UtilsHandler.java","path":"application/src/main/java/at/lucny/p2pbackup/protocol/service/handler/UtilsHandler.java"},{"key":"at.lucny.p2pbackup:p2pbackup:cloud.nextcloud/src/main/java/at/lucny/p2pbackup/cloud/nextcloud/service/NextcloudStorageServiceImpl.java","enabled":true,"qualifier":"FIL","name":"NextcloudStorageServiceImpl.java","longName":"cloud.nextcloud/src/main/java/at/lucny/p2pbackup/cloud/nextcloud/service/NextcloudStorageServiceImpl.java","path":"cloud.nextcloud/src/main/java/at/lucny/p2pbackup/cloud/nextcloud/service/NextcloudStorageServiceImpl.java"},{"key":"at.lucny.p2pbackup:p2pbackup","enabled":true,"qualifier":"TRK","name":"p2pbackup","longName":"p2pbackup"},{"key":"at.lucny.p2pbackup:p2pbackup:application/src/main/java/at/lucny/p2pbackup/upload/service/DistributionServiceImpl.java","enabled":true,"qualifier":"FIL","name":"DistributionServiceImpl.java","longName":"application/src/main/java/at/lucny/p2pbackup/upload/service/DistributionServiceImpl.java","path":"application/src/main/java/at/lucny/p2pbackup/upload/service/DistributionServiceImpl.java"},{"key":"at.lucny.p2pbackup:p2pbackup:application/src/main/java/at/lucny/p2pbackup/user/service/UserServiceImpl.java","enabled":true,"qualifier":"FIL","name":"UserServiceImpl.java","longName":"application/src/main/java/at/lucny/p2pbackup/user/service/UserServiceImpl.java","path":"application/src/main/java/at/lucny/p2pbackup/user/service/UserServiceImpl.java"},{"key":"at.lucny.p2pbackup:p2pbackup:application/src/main/java/at/lucny/p2pbackup/verification/service/VerificationServiceImpl.java","enabled":true,"qualifier":"FIL","name":"VerificationServiceImpl.java","longName":"application/src/main/java/at/lucny/p2pbackup/verification/service/VerificationServiceImpl.java","path":"application/src/main/java/at/lucny/p2pbackup/verification/service/VerificationServiceImpl.java"},{"key":"at.lucny.p2pbackup:p2pbackup:application/src/main/java/at/lucny/p2pbackup/restore/service/RestorationServiceImpl.java","enabled":true,"qualifier":"FIL","name":"RestorationServiceImpl.java","longName":"application/src/main/java/at/lucny/p2pbackup/restore/service/RestorationServiceImpl.java","path":"application/src/main/java/at/lucny/p2pbackup/restore/service/RestorationServiceImpl.java"},{"key":"at.lucny.p2pbackup:p2pbackup:cloud.filesystem/src/main/java/at/lucny/p2pbackup/cloud/filesystem/service/FilesystemStorageServiceImpl.java","enabled":true,"qualifier":"FIL","name":"FilesystemStorageServiceImpl.java","longName":"cloud.filesystem/src/main/java/at/lucny/p2pbackup/cloud/filesystem/service/FilesystemStorageServiceImpl.java","path":"cloud.filesystem/src/main/java/at/lucny/p2pbackup/cloud/filesystem/service/FilesystemStorageServiceImpl.java"}],"facets":[]}